tno/mpc/encryption_schemes/elgamal/__init__.py
tno/mpc/encryption_schemes/elgamal/elgamal.py
tno/mpc/encryption_schemes/elgamal/elgamal_additive.py
tno/mpc/encryption_schemes/elgamal/elgamal_base.py
tno/mpc/encryption_schemes/elgamal/py.typed
tno/mpc/encryption_schemes/elgamal/test/__init__.py
tno/mpc/encryption_schemes/elgamal/test/test_elgamal.py
tno/mpc/encryption_schemes/elgamal/test/test_equality.py
tno/mpc/encryption_schemes/elgamal/test/test_keygen.py
tno/mpc/encryption_schemes/elgamal/test/test_serialization.py
tno.mpc.encryption_schemes.elgamal-1.1.5.dist-info/LICENSE
tno.mpc.encryption_schemes.elgamal-1.1.5.dist-info/METADATA
tno.mpc.encryption_schemes.elgamal-1.1.5.dist-info/WHEEL
tno.mpc.encryption_schemes.elgamal-1.1.5.dist-info/top_level.txt
tno.mpc.encryption_schemes.elgamal-1.1.5.dist-info/RECORD
